causal_attribution/__init__.py
causal_attribution/data.py
causal_attribution/models.py
causal_attribution/utils.py
causal_attribution-1.1.dist-info/LICENSE
causal_attribution-1.1.dist-info/METADATA
causal_attribution-1.1.dist-info/WHEEL
causal_attribution-1.1.dist-info/top_level.txt
causal_attribution-1.1.dist-info/RECORD
