Metadata-Version: 2.1
Name: causal-attribution
Version: 1.1
Summary: Select and score features for causal inferences.
Home-page: https://github.com/rpryzant/causal_attribution
Author: Reid Pryzant
Author-email: rpryzant@stanford.edu
License: UNKNOWN
Keywords: feature selection
Platform: UNKNOWN
Classifier: Programming Language :: Python :: 3
Classifier: License :: OSI Approved :: MIT License
Classifier: Operating System :: OS Independent
Requires-Python: >=3.6
Requires-Dist: scipy
Requires-Dist: sklearn
Requires-Dist: nltk
Requires-Dist: pandas
Requires-Dist: torch (>=1.0.0)
